android_controller/__init__.py
android_controller/__main__.py
android_controller/agent.py
android_controller/client.py
android_controller/grid.py
android_controller/main.py
android_controller/mcp_server.py
android_controller/tools.py
android_controller/ui_hierarchy.py
android_controller/utils.py
opdroid-0.2.0.dist-info/METADATA
opdroid-0.2.0.dist-info/WHEEL
opdroid-0.2.0.dist-info/entry_points.txt
opdroid-0.2.0.dist-info/RECORD
