Metadata-Version: 2.4
Name: opdroid
Version: 0.2.0
Summary: LLM-controlled Android device automation via ADB
Project-URL: Homepage, https://github.com/shikhr/opdroid
Project-URL: Repository, https://github.com/shikhr/opdroid
Project-URL: Issues, https://github.com/shikhr/opdroid/issues
Author: Shikhar Mishra
License-Expression: MIT
Keywords: adb,ai-agent,android,automation,llm,vision
Classifier: Development Status :: 3 - Alpha
Classifier: Intended Audience :: Developers
Classifier: License :: OSI Approved :: MIT License
Classifier: Operating System :: OS Independent
Classifier: Programming Language :: Python :: 3
Classifier: Programming Language :: Python :: 3.10
Classifier: Programming Language :: Python :: 3.11
Classifier: Programming Language :: Python :: 3.12
Classifier: Programming Language :: Python :: 3.13
Classifier: Topic :: Software Development :: Testing
Classifier: Topic :: System :: Hardware :: Hardware Drivers
Requires-Python: >=3.10
Requires-Dist: adbutils>=2.0.0
Requires-Dist: litellm>=1.0.0
Requires-Dist: mcp>=1.0.0
Requires-Dist: pillow>=10.0.0
Requires-Dist: python-dotenv>=1.0.0
Requires-Dist: rich>=13.0.0
Requires-Dist: typer>=0.9.0
